{
  "mcpServers": {
    "supabase": {
      "type": "stdio",
      "command": "npx",
      "args": ["-y", "@supabase/mcp-server-supabase@latest", "--project-ref=furwuyjptohobrvyyzfy"],
      "env": {
        "SUPABASE_ACCESS_TOKEN": "sbp_9a38a2935f739393e072a590546ab18db373ee13"
      }
    },
    "playwright": {
      "type": "stdio",
      "command": "npx",
      "args": ["-y", "@playwright/mcp@latest"]
    },
    "context7": {
      "type": "stdio",
      "command": "npx",
      "args": ["-y", "@upstash/context7-mcp@latest"]
    },
    "zep-docs": {
      "type": "sse",
      "url": "https://docs-mcp.getzep.com/sse"
    }
  }
}
